Workbook

Sheet 0 READ ME
B2: GLOBAL MEDIA CONSUMPTION INDEX
B3: How 6 markets spend their entertainment time and money, across video, gaming, live events and audio (2020 → 2025)
B5: What this is | C5: A cross-market consumption database. Six countries: India, United States, United Kingdom, Japan, South Korea, Brazil. Five time formats: linear TV, streaming video, social and short video, gaming, music and audio. Plus market size for seven revenue formats.
B6: The headline it produces | C6: Attention is global, money is not. India consumes media time at close to the highest rate in this group and earns among the least per head. The argument is set out on sheet '11 Findings'.
B7: Colour code | C7: GREEN = reported figure from a named source. ORANGE = derived or estimated by me (method stated in the row). YELLOW = your input / assumption to change. Every row carries a source ID that maps to sheet '12 Sources'.
B8: Data quality | C8: Every row is tagged Reported, Derived or Estimated. Derived means computed from a reported figure, for example Netflix minutes from total TV time multiplied by streaming share. Estimated means scaled or inferred, so treat it as a range rather than a point.
B9: Caveat | C9: Time-spent figures are not additive across sources. Ofcom measures in-home video on TV sets. Nielsen measures TV-screen time. DataReportal measures self-reported internet time across all devices. Axis My India measures self-reported media time in India. Different definitions, samples and devices, so the categories overlap and totals double-count. Do not sum across sources. The matrices on sheets 7 to 9 only sum within one source family, and are labelled that way.
B10: Another caveat | C10: Market-size rows mix consumer spend and advertising spend, because sources do. Each row states what is included in the 'Definition' column. Never compare two rows without reading it.
B11: The index | C11: Sheet '6 Monetisation index' converts everything into one number that can be compared across markets: USD of industry revenue per 1,000 hours of attention. Dividing by attention is what makes a small market and a large one comparable.
B12: How to use this | C12: Start from a question, pull the numbers that answer it from the matrices, check the source row before using any of them, then write the finding down on the findings sheet.
B13: One more caveat | C13: The screen-economy figures on sheet 1 come from MPA and cover TV plus online video only. Gaming and publishing are outside that definition. It is applied the same way to all six countries so the comparison holds, but it is not total entertainment and media revenue. Note which definition is being used whenever a per-capita number is quoted.

Sheet 1 Country universe
A1: COUNTRY UNIVERSE, the six markets, and the money-per-attention gap
A2: Per-capita figures are the great equaliser: they strip out population and expose how differently each market monetises the same human behaviour.
A4: Country | B4: Population (m) | C4: Internet users (m) | D4: Internet penetration | E4: GDP per capita (USD) | F4: Screen economy (USD bn) | G4: Screen economy per capita (USD) | H4: Digital ad spend per capita (USD) | I4: Total media time (min/day) | J4: Annual attention (hours) | K4: Data quality / source
A5: India | B5: 1450 | C5: 900 | D5: 0.62068966 | E5: 2703 | F5: 12.4 | G5: =F5*1000/B5 -> 8.5517241 | H5: 8 | I5: 480 | J5: =I5*365/60 -> 2920 | K5: Reported, S13, S18
A6: United States | B6: 342 | C6: 320 | D6: 0.93567251 | E6: 90027 | F6: 305 | G6: =F6*1000/B6 -> 891.81287 | H6: 1000 | I6: 660 | J6: =I6*365/60 -> 4015 | K6: Reported, S13, S18
A7: United Kingdom | B7: 69 | C7: 66 | D7: 0.95652174 | E7: 52000 | F7: 28 | G7: =F7*1000/B7 -> 405.7971 | H7: 640 | I7: 660 | J7: =I7*365/60 -> 4015 | K7: Estimated, S1, S11, S18
A8: Japan | B8: 123 | C8: 106 | D8: 0.86178862 | E8: 35951 | F8: 34 | G8: =F8*1000/B8 -> 276.42276 | H8: 430 | I8: 780 | J8: =I8*365/60 -> 4745 | K8: Reported, S13, S18
A9: South Korea | B9: 52 | C9: 50 | D9: 0.96153846 | E9: 36000 | F9: 13 | G9: =F9*1000/B9 -> 250 | H9: 480 | I9: 660 | J9: =I9*365/60 -> 4015 | K9: Reported, S13, S18
A10: Brazil | B10: 212 | C10: 182 | D10: 0.85849057 | E10: 10300 | F10: 12 | G10: =F10*1000/B10 -> 56.603774 | H10: 55 | I10: 645 | J10: =I10*365/60 -> 3923.75 | K10: Estimated, S18, S11
A12: Read this | B12: India's digital ad spend per head is roughly one hundred and twenty-fifth of the US figure. That is a monetisation problem rather than a market-size problem, and it is the finding the rest of this workbook hangs on.

Sheet 2 Time database
A1: TIME DATABASE, minutes per person per day, by market and format
A2: Non-additive across sources (see READ ME). Rows marked 'Estimated' for 2020 are back-casts used only to show direction of travel.
A4: Country | B4: Format | C4: 2020 (min/day) | D4: 2025 (min/day) | E4: Change | F4: CAGR 20-25 | G4: Data quality | H4: Source
A5: India | B5: TV (linear) | C5: 78 | D5: 65 | E5: =D5-C5 -> -13 | F5: =(D5/C5)^(1/5)-1 -> -0.035807496 | G5: Reported | H5: S17
A6: India | B6: Streaming video | C6: 42 | D6: 70 | E6: =D6-C6 -> 28 | F6: =(D6/C6)^(1/5)-1 -> 0.10756634 | G6: Reported | H6: S16
A7: India | B7: Social & short video | C7: 110 | D7: 140 | E7: =D7-C7 -> 30 | F7: =(D7/C7)^(1/5)-1 -> 0.049414523 | G7: Estimated | H7: S4, S5
A8: India | B8: Gaming | C8: 60 | D8: 75 | E8: =D8-C8 -> 15 | F8: =(D8/C8)^(1/5)-1 -> 0.045639553 | G8: Reported | H8: S8
A9: India | B9: Music & audio | C9: 35 | D9: 45 | E9: =D9-C9 -> 10 | F9: =(D9/C9)^(1/5)-1 -> 0.051547497 | G9: Estimated | H9: S5, S19
A10: United States | B10: TV (linear) | C10: 130 | D10: 104 | E10: =D10-C10 -> -26 | F10: =(D10/C10)^(1/5)-1 -> -0.0436475 | G10: Derived | H10: S2
A11: United States | B11: Streaming video | C11: 75 | D11: 118 | E11: =D11-C11 -> 43 | F11: =(D11/C11)^(1/5)-1 -> 0.094874015 | G11: Derived | H11: S2
A12: United States | B12: Social & short video | C12: 105 | D12: 136 | E12: =D12-C12 -> 31 | F12: =(D12/C12)^(1/5)-1 -> 0.05310075 | G12: Reported | H12: S4
A13: United States | B13: Gaming | C13: 75 | D13: 60 | E13: =D13-C13 -> -15 | F13: =(D13/C13)^(1/5)-1 -> -0.0436475 | G13: Estimated | H13: S6
A14: United States | B14: Music & audio | C14: 55 | D14: 60 | E14: =D14-C14 -> 5 | F14: =(D14/C14)^(1/5)-1 -> 0.017554577 | G14: Estimated | H14: S9
A15: United Kingdom | B15: TV (linear) | C15: 192 | D15: 111 | E15: =D15-C15 -> -81 | F15: =(D15/C15)^(1/5)-1 -> -0.10380122 | G15: Reported | H15: S1
A16: United Kingdom | B16: Streaming video | C16: 65 | D16: 152 | E16: =D16-C16 -> 87 | F16: =(D16/C16)^(1/5)-1 -> 0.18518473 | G16: Derived | H16: S1
... A34: Brazil | B34: Music & audio | C34: 55 | D34: 70 | E34: =D34-C34 -> 15 | F34: =(D34/C34)^(1/5)-1 -> 0.049414523 | G34: Estimated | H34: S9

Sheet 3 Market size
A1: MARKET SIZE DATABASE, industry revenue in USD billion, by market and format (2025)
A2: Read the Definition column before comparing any two rows. Sources mix consumer spend and advertising spend; each row states what is included.
A4: Country | B4: Format | C4: 2020 (USD bn) | D4: 2025 (USD bn) | E4: CAGR 20-25 | F4: Data quality | G4: Source | H4: Definition, what is included
A5: India | B5: TV (linear) | C5: 10.5 | D5: 14.6 | E5: =(D5/C5)^(1/5)-1 -> 0.068151147 | F5: Derived | G5: S11 | H5: PwC traditional TV; ad + subscription
A6: India | B6: OTT video | C6: 0.6 | D6: 2.2 | E6: =(D6/C6)^(1/5)-1 -> 0.29674412 | F6: Reported | G6: S12 | H6: PwC India OTT; 216.5m subs, ARPU $7.3/sub/yr
A7: India | B7: Digital advertising | C7: 3.5 | D7: 11.6 | E7: =(D7/C7)^(1/5)-1 -> 0.27080229 | F7: Derived | G7: S14, S5 | H7: $8 per capita x population; incl. search & social
A8: India | B8: Gaming | C8: 0.9 | D8: 1.5 | E8: =(D8/C8)^(1/5)-1 -> 0.10756634 | F8: Reported | G8: S8 | H8: Lumikai video games ex-RMG; Niko Partners estimates $1.04bn
A9: India | B9: Recorded music | C9: 0.15 | D9: 0.3 | E9: =(D9/C9)^(1/5)-1 -> 0.14869836 | F9: Estimated | G9: S9 | H9: India not in IFPI top 10; scaled from PwC music+radio $1.0bn
A10: India | B10: Live events | C10: 0.5 | D10: 1.55 | E10: =(D10/C10)^(1/5)-1 -> 0.25392725 | F10: Reported | G10: S5 | H10: EY-FICCI organised live events (+44% in 2025)
A11: India | B11: Theatrical | C11: 0.5 | D11: 1.5 | E11: =(D11/C11)^(1/5)-1 -> 0.24573094 | F11: Reported | G11: S10 | H11: Gower Street/Comscore; ~5% of global box office
A12: United States | B12: TV (linear) | C12: 150 | D12: 135 | E12: =(D12/C12)^(1/5)-1 -> -0.020851638 | F12: Estimated | G12: S11 | H12: Linear TV ad + pay-TV subscription
A13: United States | B13: OTT video | C13: 60 | D13: 113.3 | E13: =(D13/C13)^(1/5)-1 -> 0.13557476 | F13: Reported | G13: S11 | H13: PwC US: largest streaming market globally
A14: United States | B14: Digital advertising | C14: 190 | D14: 295 | E14: =(D14/C14)^(1/5)-1 -> 0.091977483 | F14: Derived | G14: S11 | H14: PwC US internet advertising; ~$419.7bn by 2030 at 7.3% CAGR
A15: United States | B15: Gaming | C15: 45 | D15: 49.6 | E15: =(D15/C15)^(1/5)-1 -> 0.01965636 | F15: Reported | G15: S6 | H15: Newzoo
A16: United States | B16: Recorded music | C16: 10.5 | D16: 12.3 | E16: =(D16/C16)^(1/5)-1 -> 0.032150821 | F16: Reported | G16: S9 | H16: IFPI: 38.7% share of $31.7bn global; +3.3% YoY
... A46: Brazil | B46: Theatrical | C46: 0.2 | D46: 0.4 | E46: =(D46/C46)^(1/5)-1 -> 0.14869836 | F46: Estimated | G46: S10 | H46: Not in global top 10 territories

Sheet 4 Offline & physical
A1: OFFLINE & PHYSICAL ENTERTAINMENT, the formats you have to leave the house for
A2: Out-of-home formats are where time AND money are both still growing. They are also where per-capita gaps are widest.
A4: Country | B4: Cinema admissions per capita (per year) | C4: Data quality | D4: Source | E4: Live events spend per capita (USD/yr, est.) | F4: Note
A5: India | B5: 0.7 | C5: Estimated | D5: S10 | E5: 0.34482759 | F5: ~1.0bn admissions est. / EY-FICCI live events $1.55bn
A6: United States | B6: 2.25 | C6: Reported | D6: S10 | E6: 14.619883 | F6: 769.2m tickets / 342m population; Pollstar live $12.6bn
A7: United Kingdom | B7: 1.74 | C7: Estimated | D7: S10 | E7: 14.492754 | F7: ~120m admissions; live music ~$2.5bn
A8: Japan | B8: 1.53 | C8: Reported | D8: S10 | E8: 7.3170732 | F8: 188.76m admissions (record year)
A9: South Korea | B9: 2.1 | C9: Estimated | D9: S10 | E9: 5.7692308 | F9: ~110m admissions
A10: Brazil | B10: 0.57 | C10: Estimated | D10: S10 | E10: 1.4150943 | F10: ~120m admissions

Sheet 5 Streaming & penetration
A1: STREAMING PENETRATION, who actually pays, and how much each payer is worth
A4: Country | B4: Netflix subscribers (m) | C4: Data quality | D4: Paid OTT subscriptions (m) | E4: Paid subs per 100 people | F4: Netflix penetration of population | G4: Source | H4: Note
A5: India | B5: 13.3 | C5: Estimated | D5: 216.5 | E5: =D5/A5*100 | F5: =B5/1450*100 | G5: S4 / S12
A6: United States | B6: 87.8 | C6: Estimated | D6: 245 | E6: =D6/A6*100 | F6: =B6/342*100 | G6: S4 / S11
A7: United Kingdom | B7: 19.8 | C7: Estimated | D7: 45 | E7: =D7/A7*100 | F7: =B7/69*100 | G7: S4 / S11
A8: Japan | B8: 9.8 | C8: Estimated | D8: 32 | E8: =D8/A8*100 | F8: =B8/123*100 | G8: S4 / S11
A9: South Korea | B9: 9 | C9: Estimated | D9: 18 | E9: =D9/A9*100 | F9: =B9/52*100 | G9: S4 / S11
A10: Brazil | B10: 17.9 | C10: Estimated | D10: 42 | E10: =D10/A10*100 | F10: =B10/212*100 | G10: S4 / S11
A12: India vs US, the number that matters | B12: India has 216.5m paid OTT subscriptions, the third-largest base in the world, and each subscription is worth only $7.3 a year to the platform. The US OTT market is 51x larger in revenue on a base only ~13% bigger.

Sheet 6 Monetisation index
A1: MONETISATION INDEX, USD of screen revenue per 1,000 hours of attention
A2: The one comparable number in this workbook: how much money the industry earns for each hour a population spends consuming media. It strips out population, currency and market size.
A4: Country | B4: Screen economy (USD bn) | C4: Screen economy per capita (USD) | D4: Attention: 5-format sum (hrs/yr) | E4: USD per 1,000 hours (5-format) | F4: Attention: all-media measure (hrs/yr) | G4: USD per 1,000 hours (all-media) | H4: Index (US = 100) | I4: Rank | J4: Interpretation
A5: India | B5: 12.4 | C5: =B5*1000/1450 -> 8.5517241 | D5: =SUMIFS('2 Time database'!$D$5:$D$34,'2 Time database'!$A$5:$A$34,$A5)*365/60 -> 2402.9167 | E5: =C5/(D5/1000) -> 3.5588933 | F5: =480*365/60 -> 2920 | G5: =C5/(F5/1000) -> 2.9286727 | H5: =E5/$E$6*100 -> 1.1604081 | I5: =RANK(E5,$E$5:$E$10) -> 6 | J5: World-scale attention, startup-scale revenue. Every 1,000 hours of Indian attention earns the industry about USD 4.
A6: United States | B6: 305 | C6: =B6*1000/342 -> 891.81287 | D6: =SUMIFS('2 Time database'!$D$5:$D$34,'2 Time database'!$A$5:$A$34,$A6)*365/60 -> 2907.8333 | E6: =C6/(D6/1000) -> 306.69325 | F6: =660*365/60 -> 4015 | G6: =C6/(F6/1000) -> 222.12027 | H6: =E6/$E$6*100 -> 100 | I6: =RANK(E6,$E$5:$E$10) -> 1 | J6: The benchmark. An American hour of attention is worth roughly 86x an Indian hour.
A7: United Kingdom | B7: 28 | C7: =B7*1000/69 -> 405.7971 | D7: =SUMIFS('2 Time database'!$D$5:$D$34,'2 Time database'!$A$5:$A$34,$A7)*365/60 -> 2859.1667 | E7: =C7/(D7/1000) -> 141.92845 | F7: =660*365/60 -> 4015 | G7: =C7/(F7/1000) -> 101.07026 | H7: =E7/$E$6*100 -> 46.277005 | I7: =RANK(E7,$E$5:$E$10) -> 2 | J7: High monetisation on a shrinking habit: total in-home video time fell in 2025.
A8: Japan | B8: 34 | C8: =B8*1000/123 -> 276.42276 | D8: =SUMIFS('2 Time database'!$D$5:$D$34,'2 Time database'!$A$5:$A$34,$A8)*365/60 -> 2536.75 | E8: =C8/(D8/1000) -> 108.96729 | F8: =780*365/60 -> 4745 | G8: =C8/(F8/1000) -> 58.255588 | H8: =E8/$E$6*100 -> 35.529731 | I8: =RANK(E8,$E$5:$E$10) -> 3 | J8: Most media time of the six, mid-tier monetisation, an old, rich, patient market.
A9: South Korea | B9: 13 | C9: =B9*1000/52 -> 250 | D9: =SUMIFS('2 Time database'!$D$5:$D$34,'2 Time database'!$A$5:$A$34,$A9)*365/60 -> 2822.6667 | E9: =C9/(D9/1000) -> 88.568729 | F9: =660*365/60 -> 4015 | G9: =C9/(F9/1000) -> 62.266501 | H9: =E9/$E$6*100 -> 28.878604 | I9: =RANK(E9,$E$5:$E$10) -> 4 | J9: Small population, high yield: monetisation follows income AND product design.
A10: Brazil | B10: 12 | C10: =B10*1000/212 -> 56.603774 | D10: =SUMIFS('2 Time database'!$D$5:$D$34,'2 Time database'!$A$5:$A$34,$A10)*365/60 -> 3917.6667 | E10: =C10/(D10/1000) -> 14.448338 | F10: =645*365/60 -> 3923.75 | G10: =C10/(F10/1000) -> 14.425938 | H10: =E10/$E$6*100 -> 4.7110063 | I10: =RANK(E10,$E$5:$E$10) -> 5 | J10: The world's social-media champion by time, monetised at emerging-market rates.
A12: Method note | B12: Two denominators are shown deliberately. '5-format sum' adds only the five formats tracked on sheet 2, internally consistent, but a lower bound because radio, print, podcasts and out-of-home time are excluded. 'All-media measure' uses published total media time per person (The Drum, Mar-2026), a broader definition that overlaps in places. Both produce the same ranking. Numerator = MPA screen economy (TV + online video), which excludes gaming and publishing. Use the index for relative comparison, never as an accounting identity.

Sheet 7 Matrix - time
A1: MATRIX VIEW, minutes per person per day (2025)
A2: Formula-driven from sheet '2 Time database' (SUMIFS). Change the database and this updates.
A4: Country | B4: TV (linear) | C4: Streaming video | D4: Social & short video | E4: Gaming | F4: Music & audio | G4: Total | H4: Note
A5: India | B5: =SUMIFS('2 Time database'!$D$5:$D$34,'2 Time database'!$A$5:$A$34,$A5,'2 Time database'!$B$5:$B$34,B$4) -> 65 | C5: =SUMIFS('2 Time database'!$D$5:$D$34,'2 Time database'!$A$5:$A$34,$A5,'2 Time database'!$B$5:$B$34,C$4) -> 70 | D5: =SUMIFS('2 Time database'!$D$5:$D$34,'2 Time database'!$A$5:$A$34,$A5,'2 Time database'!$B$5:$B$34,D$4) -> 140 | E5: =SUMIFS('2 Time database'!$D$5:$D$34,'2 Time database'!$A$5:$A$34,$A5,'2 Time database'!$B$5:$B$34,E$4) -> 75 | F5: =SUMIFS('2 Time database'!$D$5:$D$34,'2 Time database'!$A$5:$A$34,$A5,'2 Time database'!$B$5:$B$34,F$4) -> 45 | G5: =SUM(B5:F5) -> 395 | H5: Highest social + gaming time of the six, lowest TV time, a mobile-first market, not a TV market.
A6: United States | B6: =SUMIFS('2 Time database'!$D$5:$D$34,'2 Time database'!$A$5:$A$34,$A6,'2 Time database'!$B$5:$B$34,B$4) -> 104 | C6: =SUMIFS('2 Time database'!$D$5:$D$34,'2 Time database'!$A$5:$A$34,$A6,'2 Time database'!$B$5:$B$34,C$4) -> 118 | D6: =SUMIFS('2 Time database'!$D$5:$D$34,'2 Time database'!$A$5:$A$34,$A6,'2 Time database'!$B$5:$B$34,D$4) -> 136 | E6: =SUMIFS('2 Time database'!$D$5:$D$34,'2 Time database'!$A$5:$A$34,$A6,'2 Time database'!$B$5:$B$34,E$4) -> 60 | F6: =SUMIFS('2 Time database'!$D$5:$D$34,'2 Time database'!$A$5:$A$34,$A6,'2 Time database'!$B$5:$B$34,F$4) -> 60 | G6: =SUM(B6:F6) -> 478 | H6: TV time is half the total and half of it is now streaming, not broadcast.
A7: United Kingdom | B7: =SUMIFS('2 Time database'!$D$5:$D$34,'2 Time database'!$A$5:$A$34,$A7,'2 Time database'!$B$5:$B$34,B$4) -> 111 | C7: =SUMIFS('2 Time database'!$D$5:$D$34,'2 Time database'!$A$5:$A$34,$A7,'2 Time database'!$B$5:$B$34,C$4) -> 152 | D7: =SUMIFS('2 Time database'!$D$5:$D$34,'2 Time database'!$A$5:$A$34,$A7,'2 Time database'!$B$5:$B$34,D$4) -> 97 | E7: =SUMIFS('2 Time database'!$D$5:$D$34,'2 Time database'!$A$5:$A$34,$A7,'2 Time database'!$B$5:$B$34,E$4) -> 55 | F7: =SUMIFS('2 Time database'!$D$5:$D$34,'2 Time database'!$A$5:$A$34,$A7,'2 Time database'!$B$5:$B$34,F$4) -> 55 | G7: =SUM(B7:F7) -> 470 | H7: Most video-saturated market: 4h23m of in-home video a day, of which only 1h51m is broadcast.
A8: Japan | B8: =SUMIFS('2 Time database'!$D$5:$D$34,'2 Time database'!$A$5:$A$34,$A8,'2 Time database'!$B$5:$B$34,B$4) -> 217 | C8: =SUMIFS('2 Time database'!$D$5:$D$34,'2 Time database'!$A$5:$A$34,$A8,'2 Time database'!$B$5:$B$34,C$4) -> 50 | D8: =SUMIFS('2 Time database'!$D$5:$D$34,'2 Time database'!$A$5:$A$34,$A8,'2 Time database'!$B$5:$B$34,D$4) -> 50 | E8: =SUMIFS('2 Time database'!$D$5:$D$34,'2 Time database'!$A$5:$A$34,$A8,'2 Time database'!$B$5:$B$34,E$4) -> 60 | F8: =SUMIFS('2 Time database'!$D$5:$D$34,'2 Time database'!$A$5:$A$34,$A8,'2 Time database'!$B$5:$B$34,F$4) -> 40 | G8: =SUM(B8:F8) -> 417 | H8: The outlier: TV still dominates and social time is the lowest of any major market.
A9: South Korea | B9: =SUMIFS('2 Time database'!$D$5:$D$34,'2 Time database'!$A$5:$A$34,$A9,'2 Time database'!$B$5:$B$34,B$4) -> 199 | C9: =SUMIFS('2 Time database'!$D$5:$D$34,'2 Time database'!$A$5:$A$34,$A9,'2 Time database'!$B$5:$B$34,C$4) -> 55 | D9: =SUMIFS('2 Time database'!$D$5:$D$34,'2 Time database'!$A$5:$A$34,$A9,'2 Time database'!$B$5:$B$34,D$4) -> 70 | E9: =SUMIFS('2 Time database'!$D$5:$D$34,'2 Time database'!$A$5:$A$34,$A9,'2 Time database'!$B$5:$B$34,E$4) -> 90 | F9: =SUMIFS('2 Time database'!$D$5:$D$34,'2 Time database'!$A$5:$A$34,$A9,'2 Time database'!$B$5:$B$34,F$4) -> 50 | G9: =SUM(B9:F9) -> 464 | H9: TV and gaming both high, a market with two mass habits, not one.
A10: Brazil | B10: =SUMIFS('2 Time database'!$D$5:$D$34,'2 Time database'!$A$5:$A$34,$A10,'2 Time database'!$B$5:$B$34,B$4) -> 210 | C10: =SUMIFS('2 Time database'!$D$5:$D$34,'2 Time database'!$A$5:$A$34,$A10,'2 Time database'!$B$5:$B$34,C$4) -> 80 | D10: =SUMIFS('2 Time database'!$D$5:$D$34,'2 Time database'!$A$5:$A$34,$A10,'2 Time database'!$B$5:$B$34,D$4) -> 229 | E10: =SUMIFS('2 Time database'!$D$5:$D$34,'2 Time database'!$A$5:$A$34,$A10,'2 Time database'!$B$5:$B$34,E$4) -> 55 | F10: =SUMIFS('2 Time database'!$D$5:$D$34,'2 Time database'!$A$5:$A$34,$A10,'2 Time database'!$B$5:$B$34,F$4) -> 70 | G10: =SUM(B10:F10) -> 644 | H10: The social-media champion: 3h49m a day on social, more than any other market measured.
A11: Average | B11: =AVERAGE(B5:B10) -> 151 | C11: =AVERAGE(C5:C10) -> 87.5 | D11: =AVERAGE(D5:D10) -> 120.33333 | E11: =AVERAGE(E5:E10) -> 65.833333 | F11: =AVERAGE(F5:F10) -> 53.333333 | G11: =AVERAGE(G5:G10) -> 478

Sheet 8 Matrix - market size
A1: MATRIX VIEW, industry revenue, USD bn (2025)
A2: Formula-driven from sheet '3 Market size'. Definitions differ by row, read the definition column before quoting.
A4: Country | B4: TV (linear) | C4: OTT video | D4: Digital advertising | E4: Gaming | F4: Recorded music | G4: Live events | H4: Theatrical | I4: Total | J4: Note
A5: India | B5: =SUMIFS('3 Market size'!$D$5:$D$46,'3 Market size'!$A$5:$A$46,$A5,'3 Market size'!$B$5:$B$46,B$4) -> 14.6 | C5: =SUMIFS('3 Market size'!$D$5:$D$46,'3 Market size'!$A$5:$A$46,$A5,'3 Market size'!$B$5:$B$46,C$4) -> 2.2 | D5: =SUMIFS('3 Market size'!$D$5:$D$46,'3 Market size'!$A$5:$A$46,$A5,'3 Market size'!$B$5:$B$46,D$4) -> 11.6 | E5: =SUMIFS('3 Market size'!$D$5:$D$46,'3 Market size'!$A$5:$A$46,$A5,'3 Market size'!$B$5:$B$46,E$4) -> 1.5 | F5: =SUMIFS('3 Market size'!$D$5:$D$46,'3 Market size'!$A$5:$A$46,$A5,'3 Market size'!$B$5:$B$46,F$4) -> 0.3 | G5: =SUMIFS('3 Market size'!$D$5:$D$46,'3 Market size'!$A$5:$A$46,$A5,'3 Market size'!$B$5:$B$46,G$4) -> 1.55 | H5: =SUMIFS('3 Market size'!$D$5:$D$46,'3 Market size'!$A$5:$A$46,$A5,'3 Market size'!$B$5:$B$46,H$4) -> 1.5 | I5: =SUM(B5:H5) -> 33.25 | J5: Every format is small in dollars and looks large in users. The wedge is monetisation, not audience.
A6: United States | B6: =SUMIFS('3 Market size'!$D$5:$D$46,'3 Market size'!$A$5:$A$46,$A6,'3 Market size'!$B$5:$B$46,B$4) -> 135 | C6: =SUMIFS('3 Market size'!$D$5:$D$46,'3 Market size'!$A$5:$A$46,$A6,'3 Market size'!$B$5:$B$46,C$4) -> 113.3 | D6: =SUMIFS('3 Market size'!$D$5:$D$46,'3 Market size'!$A$5:$A$46,$A6,'3 Market size'!$B$5:$B$46,D$4) -> 295 | E6: =SUMIFS('3 Market size'!$D$5:$D$46,'3 Market size'!$A$5:$A$46,$A6,'3 Market size'!$B$5:$B$46,E$4) -> 49.6 | F6: =SUMIFS('3 Market size'!$D$5:$D$46,'3 Market size'!$A$5:$A$46,$A6,'3 Market size'!$B$5:$B$46,F$4) -> 12.3 | G6: =SUMIFS('3 Market size'!$D$5:$D$46,'3 Market size'!$A$5:$A$46,$A6,'3 Market size'!$B$5:$B$46,G$4) -> 12.6 | H6: =SUMIFS('3 Market size'!$D$5:$D$46,'3 Market size'!$A$5:$A$46,$A6,'3 Market size'!$B$5:$B$46,H$4) -> 8.9 | I6: =SUM(B6:H6) -> 626.7 | J6: OTT video alone ($113bn) is 51x India's entire OTT market on a 13% larger paying base.
A7: United Kingdom | B7: =SUMIFS('3 Market size'!$D$5:$D$46,'3 Market size'!$A$5:$A$46,$A7,'3 Market size'!$B$5:$B$46,B$4) -> 12 | C7: =SUMIFS('3 Market size'!$D$5:$D$46,'3 Market size'!$A$5:$A$46,$A7,'3 Market size'!$B$5:$B$46,C$4) -> 7 | D7: =SUMIFS('3 Market size'!$D$5:$D$46,'3 Market size'!$A$5:$A$46,$A7,'3 Market size'!$B$5:$B$46,D$4) -> 30 | E7: =SUMIFS('3 Market size'!$D$5:$D$46,'3 Market size'!$A$5:$A$46,$A7,'3 Market size'!$B$5:$B$46,E$4) -> 6.8 | F7: =SUMIFS('3 Market size'!$D$5:$D$46,'3 Market size'!$A$5:$A$46,$A7,'3 Market size'!$B$5:$B$46,F$4) -> 1.9 | G7: =SUMIFS('3 Market size'!$D$5:$D$46,'3 Market size'!$A$5:$A$46,$A7,'3 Market size'!$B$5:$B$46,G$4) -> 2.5 | H7: =SUMIFS('3 Market size'!$D$5:$D$46,'3 Market size'!$A$5:$A$46,$A7,'3 Market size'!$B$5:$B$46,H$4) -> 1.5 | I7: =SUM(B7:H7) -> 61.7 | J7: Gaming and digital advertising carry a market whose traditional TV is shrinking.
A8: Japan | B8: =SUMIFS('3 Market size'!$D$5:$D$46,'3 Market size'!$A$5:$A$46,$A8,'3 Market size'!$B$5:$B$46,B$4) -> 22 | C8: =SUMIFS('3 Market size'!$D$5:$D$46,'3 Market size'!$A$5:$A$46,$A8,'3 Market size'!$B$5:$B$46,C$4) -> 6 | D8: =SUMIFS('3 Market size'!$D$5:$D$46,'3 Market size'!$A$5:$A$46,$A8,'3 Market size'!$B$5:$B$46,D$4) -> 25 | E8: =SUMIFS('3 Market size'!$D$5:$D$46,'3 Market size'!$A$5:$A$46,$A8,'3 Market size'!$B$5:$B$46,E$4) -> 17.6 | F8: =SUMIFS('3 Market size'!$D$5:$D$46,'3 Market size'!$A$5:$A$46,$A8,'3 Market size'!$B$5:$B$46,F$4) -> 3 | G8: =SUMIFS('3 Market size'!$D$5:$D$46,'3 Market size'!$A$5:$A$46,$A8,'3 Market size'!$B$5:$B$46,G$4) -> 1.5 | H8: =SUMIFS('3 Market size'!$D$5:$D$46,'3 Market size'!$A$5:$A$46,$A8,'3 Market size'!$B$5:$B$46,H$4) -> 1.8 | I8: =SUM(B8:H8) -> 76.9 | J8: Gaming ($17.6bn) is bigger than Japan's TV and cinema markets combined.
A9: South Korea | B9: =SUMIFS('3 Market size'!$D$5:$D$46,'3 Market size'!$A$5:$A$46,$A9,'3 Market size'!$B$5:$B$46,B$4) -> 6 | C9: =SUMIFS('3 Market size'!$D$5:$D$46,'3 Market size'!$A$5:$A$46,$A9,'3 Market size'!$B$5:$B$46,C$4) -> 2.5 | D9: =SUMIFS('3 Market size'!$D$5:$D$46,'3 Market size'!$A$5:$A$46,$A9,'3 Market size'!$B$5:$B$46,D$4) -> 8 | E9: =SUMIFS('3 Market size'!$D$5:$D$46,'3 Market size'!$A$5:$A$46,$A9,'3 Market size'!$B$5:$B$46,E$4) -> 8.3 | F9: =SUMIFS('3 Market size'!$D$5:$D$46,'3 Market size'!$A$5:$A$46,$A9,'3 Market size'!$B$5:$B$46,F$4) -> 0.9 | G9: =SUMIFS('3 Market size'!$D$5:$D$46,'3 Market size'!$A$5:$A$46,$A9,'3 Market size'!$B$5:$B$46,G$4) -> 0.6 | H9: =SUMIFS('3 Market size'!$D$5:$D$46,'3 Market size'!$A$5:$A$46,$A9,'3 Market size'!$B$5:$B$46,H$4) -> 0.7 | I9: =SUM(B9:H9) -> 27 | J9: Gaming is the largest format in the country, ahead of TV. Almost nowhere else on earth.
A10: Brazil | B10: =SUMIFS('3 Market size'!$D$5:$D$46,'3 Market size'!$A$5:$A$46,$A10,'3 Market size'!$B$5:$B$46,B$4) -> 9 | C10: =SUMIFS('3 Market size'!$D$5:$D$46,'3 Market size'!$A$5:$A$46,$A10,'3 Market size'!$B$5:$B$46,C$4) -> 3.5 | D10: =SUMIFS('3 Market size'!$D$5:$D$46,'3 Market size'!$A$5:$A$46,$A10,'3 Market size'!$B$5:$B$46,D$4) -> 8 | E10: =SUMIFS('3 Market size'!$D$5:$D$46,'3 Market size'!$A$5:$A$46,$A10,'3 Market size'!$B$5:$B$46,E$4) -> 2.8 | F10: =SUMIFS('3 Market size'!$D$5:$D$46,'3 Market size'!$A$5:$A$46,$A10,'3 Market size'!$B$5:$B$46,F$4) -> 0.55 | G10: =SUMIFS('3 Market size'!$D$5:$D$46,'3 Market size'!$A$5:$A$46,$A10,'3 Market size'!$B$5:$B$46,G$4) -> 0.8 | H10: =SUMIFS('3 Market size'!$D$5:$D$46,'3 Market size'!$A$5:$A$46,$A10,'3 Market size'!$B$5:$B$46,H$4) -> 0.4 | I10: =SUM(B10:H10) -> 25.05 | J10: Digital advertising and gaming lead; Brazil is IFPI's fastest-rising top-10 music market.
A11: Average | B11: =AVERAGE(B5:B10) -> 33.1 | C11: =AVERAGE(C5:C10) -> 22.416667 | D11: =AVERAGE(D5:D10) -> 62.933333 | E11: =AVERAGE(E5:E10) -> 14.433333 | F11: =AVERAGE(F5:F10) -> 3.1583333 | G11: =AVERAGE(G5:G10) -> 3.2583333 | H11: =AVERAGE(H5:H10) -> 2.4666667 | I11: =AVERAGE(I5:I10) -> 141.76667

Sheet 9 Matrix - spend per capita
A1: MATRIX VIEW, industry revenue per capita, USD per person per year (2025)
A2: Market size divided by population. This is the sheet to open when someone says 'India is a huge market'.
A4: Country | B4: TV (linear) | C4: OTT video | D4: Digital advertising | E4: Gaming | F4: Recorded music | G4: Live events | H4: Theatrical | I4: Total
A5: India | B5: =SUMIFS('3 Market size'!$D$5:$D$46,'3 Market size'!$A$5:$A$46,$A5,'3 Market size'!$B$5:$B$46,B$4)/1450*1000 -> 10.068966 | C5: =SUMIFS('3 Market size'!$D$5:$D$46,'3 Market size'!$A$5:$A$46,$A5,'3 Market size'!$B$5:$B$46,C$4)/1450*1000 -> 1.5172414 | D5: =SUMIFS('3 Market size'!$D$5:$D$46,'3 Market size'!$A$5:$A$46,$A5,'3 Market size'!$B$5:$B$46,D$4)/1450*1000 -> 8 | E5: =SUMIFS('3 Market size'!$D$5:$D$46,'3 Market size'!$A$5:$A$46,$A5,'3 Market size'!$B$5:$B$46,E$4)/1450*1000 -> 1.0344828 | F5: =SUMIFS('3 Market size'!$D$5:$D$46,'3 Market size'!$A$5:$A$46,$A5,'3 Market size'!$B$5:$B$46,F$4)/1450*1000 -> 0.20689655 | G5: =SUMIFS('3 Market size'!$D$5:$D$46,'3 Market size'!$A$5:$A$46,$A5,'3 Market size'!$B$5:$B$46,G$4)/1450*1000 -> 1.0689655 | H5: =SUMIFS('3 Market size'!$D$5:$D$46,'3 Market size'!$A$5:$A$46,$A5,'3 Market size'!$B$5:$B$46,H$4)/1450*1000 -> 1.0344828 | I5: =SUM(B5:H5) -> 22.931034
A6: United States | B6: =SUMIFS('3 Market size'!$D$5:$D$46,'3 Market size'!$A$5:$A$46,$A6,'3 Market size'!$B$5:$B$46,B$4)/342*1000 -> 394.73684 | C6: =SUMIFS('3 Market size'!$D$5:$D$46,'3 Market size'!$A$5:$A$46,$A6,'3 Market size'!$B$5:$B$46,C$4)/342*1000 -> 331.28655 | D6: =SUMIFS('3 Market size'!$D$5:$D$46,'3 Market size'!$A$5:$A$46,$A6,'3 Market size'!$B$5:$B$46,D$4)/342*1000 -> 862.5731 | E6: =SUMIFS('3 Market size'!$D$5:$D$46,'3 Market size'!$A$5:$A$46,$A6,'3 Market size'!$B$5:$B$46,E$4)/342*1000 -> 145.02924 | F6: =SUMIFS('3 Market size'!$D$5:$D$46,'3 Market size'!$A$5:$A$46,$A6,'3 Market size'!$B$5:$B$46,F$4)/342*1000 -> 35.964912 | G6: =SUMIFS('3 Market size'!$D$5:$D$46,'3 Market size'!$A$5:$A$46,$A6,'3 Market size'!$B$5:$B$46,G$4)/342*1000 -> 36.842105 | H6: =SUMIFS('3 Market size'!$D$5:$D$46,'3 Market size'!$A$5:$A$46,$A6,'3 Market size'!$B$5:$B$46,H$4)/342*1000 -> 26.023392 | I6: =SUM(B6:H6) -> 1832.4561
A7: United Kingdom | B7: =SUMIFS('3 Market size'!$D$5:$D$46,'3 Market size'!$A$5:$A$46,$A7,'3 Market size'!$B$5:$B$46,B$4)/69*1000 -> 173.91304 | C7: =SUMIFS('3 Market size'!$D$5:$D$46,'3 Market size'!$A$5:$A$46,$A7,'3 Market size'!$B$5:$B$46,C$4)/69*1000 -> 101.44928 | D7: =SUMIFS('3 Market size'!$D$5:$D$46,'3 Market size'!$A$5:$A$46,$A7,'3 Market size'!$B$5:$B$46,D$4)/69*1000 -> 434.78261 | E7: =SUMIFS('3 Market size'!$D$5:$D$46,'3 Market size'!$A$5:$A$46,$A7,'3 Market size'!$B$5:$B$46,E$4)/69*1000 -> 98.550725 | F7: =SUMIFS('3 Market size'!$D$5:$D$46,'3 Market size'!$A$5:$A$46,$A7,'3 Market size'!$B$5:$B$46,F$4)/69*1000 -> 27.536232 | G7: =SUMIFS('3 Market size'!$D$5:$D$46,'3 Market size'!$A$5:$A$46,$A7,'3 Market size'!$B$5:$B$46,G$4)/69*1000 -> 36.231884 | H7: =SUMIFS('3 Market size'!$D$5:$D$46,'3 Market size'!$A$5:$A$46,$A7,'3 Market size'!$B$5:$B$46,H$4)/69*1000 -> 21.73913 | I7: =SUM(B7:H7) -> 894.2029
A8: Japan | B8: =SUMIFS('3 Market size'!$D$5:$D$46,'3 Market size'!$A$5:$A$46,$A8,'3 Market size'!$B$5:$B$46,B$4)/123*1000 -> 178.86179 | C8: =SUMIFS('3 Market size'!$D$5:$D$46,'3 Market size'!$A$5:$A$46,$A8,'3 Market size'!$B$5:$B$46,C$4)/123*1000 -> 48.780488 | D8: =SUMIFS('3 Market size'!$D$5:$D$46,'3 Market size'!$A$5:$A$46,$A8,'3 Market size'!$B$5:$B$46,D$4)/123*1000 -> 203.25203 | E8: =SUMIFS('3 Market size'!$D$5:$D$46,'3 Market size'!$A$5:$A$46,$A8,'3 Market size'!$B$5:$B$46,E$4)/123*1000 -> 143.08943 | F8: =SUMIFS('3 Market size'!$D$5:$D$46,'3 Market size'!$A$5:$A$46,$A8,'3 Market size'!$B$5:$B$46,F$4)/123*1000 -> 24.390244 | G8: =SUMIFS('3 Market size'!$D$5:$D$46,'3 Market size'!$A$5:$A$46,$A8,'3 Market size'!$B$5:$B$46,G$4)/123*1000 -> 12.195122 | H8: =SUMIFS('3 Market size'!$D$5:$D$46,'3 Market size'!$A$5:$A$46,$A8,'3 Market size'!$B$5:$B$46,H$4)/123*1000 -> 14.634146 | I8: =SUM(B8:H8) -> 625.20325
A9: South Korea | B9: =SUMIFS('3 Market size'!$D$5:$D$46,'3 Market size'!$A$5:$A$46,$A9,'3 Market size'!$B$5:$B$46,B$4)/52*1000 -> 115.38462 | C9: =SUMIFS('3 Market size'!$D$5:$D$46,'3 Market size'!$A$5:$A$46,$A9,'3 Market size'!$B$5:$B$46,C$4)/52*1000 -> 48.076923 | D9: =SUMIFS('3 Market size'!$D$5:$D$46,'3 Market size'!$A$5:$A$46,$A9,'3 Market size'!$B$5:$B$46,D$4)/52*1000 -> 153.84615 | E9: =SUMIFS('3 Market size'!$D$5:$D$46,'3 Market size'!$A$5:$A$46,$A9,'3 Market size'!$B$5:$B$46,E$4)/52*1000 -> 159.61538 | F9: =SUMIFS('3 Market size'!$D$5:$D$46,'3 Market size'!$A$5:$A$46,$A9,'3 Market size'!$B$5:$B$46,F$4)/52*1000 -> 17.307692 | G9: =SUMIFS('3 Market size'!$D$5:$D$46,'3 Market size'!$A$5:$A$46,$A9,'3 Market size'!$B$5:$B$46,G$4)/52*1000 -> 11.538462 | H9: =SUMIFS('3 Market size'!$D$5:$D$46,'3 Market size'!$A$5:$A$46,$A9,'3 Market size'!$B$5:$B$46,H$4)/52*1000 -> 13.461538 | I9: =SUM(B9:H9) -> 519.23077
A10: Brazil | B10: =SUMIFS('3 Market size'!$D$5:$D$46,'3 Market size'!$A$5:$A$46,$A10,'3 Market size'!$B$5:$B$46,B$4)/212*1000 -> 42.45283 | C10: =SUMIFS('3 Market size'!$D$5:$D$46,'3 Market size'!$A$5:$A$46,$A10,'3 Market size'!$B$5:$B$46,C$4)/212*1000 -> 16.509434 | D10: =SUMIFS('3 Market size'!$D$5:$D$46,'3 Market size'!$A$5:$A$46,$A10,'3 Market size'!$B$5:$B$46,D$4)/212*1000 -> 37.735849 | E10: =SUMIFS('3 Market size'!$D$5:$D$46,'3 Market size'!$A$5:$A$46,$A10,'3 Market size'!$B$5:$B$46,E$4)/212*1000 -> 13.207547 | F10: =SUMIFS('3 Market size'!$D$5:$D$46,'3 Market size'!$A$5:$A$46,$A10,'3 Market size'!$B$5:$B$46,F$4)/212*1000 -> 2.5943396 | G10: =SUMIFS('3 Market size'!$D$5:$D$46,'3 Market size'!$A$5:$A$46,$A10,'3 Market size'!$B$5:$B$46,G$4)/212*1000 -> 3.7735849 | H10: =SUMIFS('3 Market size'!$D$5:$D$46,'3 Market size'!$A$5:$A$46,$A10,'3 Market size'!$B$5:$B$46,H$4)/212*1000 -> 1.8867925 | I10: =SUM(B10:H10) -> 118.16038
A11: Average | B11: =AVERAGE(B5:B10) -> 152.56968 | C11: =AVERAGE(C5:C10) -> 91.269985 | D11: =AVERAGE(D5:D10) -> 283.36496 | E11: =AVERAGE(E5:E10) -> 93.421135 | F11: =AVERAGE(F5:F10) -> 18.000053 | G11: =AVERAGE(G5:G10) -> 16.941687 | H11: =AVERAGE(H5:H10) -> 13.129914 | I11: =AVERAGE(I5:I10) -> 668.69741

Sheet 10 India deep dive
A1: INDIA DEEP DIVE, the largest consumption market that cannot yet pay for itself
A3: Metric | B3: Value | C3: Data quality | D3: Source / note
A4: M&E sector revenue 2025 (INR trillion) | B4: 2.78 | C4: Reported | D4: FICCI-EY Mar-2026; +9% YoY; projected INR 3.3tn by 2028
A5: Total advertising revenue (INR bn) | B5: 1500 | C5: Reported | D5: FICCI-EY 2026; +13.5%; 0.41% of GDP
A6: Digital advertising (INR bn) | B6: 947 | C6: Reported | D6: FICCI-EY 2026; 63% of all ad spend; +26%
A7: Linear TV advertising (INR bn) | B7: 263 | C7: Reported | D7: FICCI-EY 2026 / Statista; -10% in 2025; advertisers down 3%
A8: Connected TV advertising (INR bn) | B8: 99 | C8: Reported | D8: FICCI-EY 2026; +42%; CTV units 40m (from 30m)
A9: Pay TV households change (mn) | B9: -11 | C9: Reported | D9: FICCI-EY 2026; structural cord-shrinking, not cord-cutting
A10: OTT users (mn) | B10: 601 | C10: Reported | D10: Ormax 2025
A11: Paid OTT subscriptions (mn) | B11: 216.5 | C11: Reported | D11: PwC 2026-30 India perspective
A12: OTT revenue (USD bn) | B12: 2.2 | C12: Reported | D12: PwC India 2026; to USD 3.6bn by 2030 at 10.2% CAGR
A13: OTT ARPU (USD per subscription per year) | B13: 7.3 | C13: Reported | D13: PwC India 2026, the number that defines the market
A14: Smartphone screen time 2025 (trillion hours) | B14: 1.23 | C14: Reported | D14: FICCI-EY 2026; 59% of it is M&E consumption
A15: Digital ad spend per capita (USD) | B15: 8 | C15: Reported | D15: Redseer Apr-2026; US ~$1,000, China ~$120
... A28: News subscriptions (mn) | B28: 4 | C28: Reported | D28: FICCI-EY 2026; less than 3% of print revenue
A30: THE THREE SENTENCES THAT MATTER
A31: 1. India consumes like a rich country and pays like a poor one: 1.23 trillion hours of smartphone screen time a year, earning the industry USD 8.4 per person.
A32: 2. The paying base is not the problem, 216.5m OTT subscriptions, 3rd largest in the world. The price is: USD 7.3 per subscription per year.
A33: 3. Which means every rupee of growth must come from ARPU, advertising yield or new formats (CTV, live, gaming), not from adding more users, because the users are already here.

Sheet 11 Findings
A1: FINDINGS, the argument this workbook exists to support
A3: # | B3: Finding | C3: Evidence | D3: So what for a client | E3: Confidence
A4: 1 | B4: Attention is global; money is local. | C4: India: 1.23tn hours of smartphone screen time a year, 59% of it M&E. But USD 8.4 of screen revenue per head vs USD 889 in the US, a ~106x gap, against a ~11x GDP per-capita gap. | D4: Judge an Indian media business on revenue per hour of attention, not on reach. Reach is free; yield is the business. | E4: High
A5: 2 | B5: The paying base is already built. The price is not. | C5: India has 216.5m paid OTT subscriptions, 3rd largest in the world, at USD 7.3 per subscription per year. The US OTT market is 51x larger in revenue on a base only ~13% larger. | D5: Stop funding user acquisition as the primary growth lever. ARPU, advertising yield and bundling are the levers left. | E5: High
A6: 3 | B6: Consumption is migrating, not growing. | C6: UK total in-home video fell 7 minutes in 2025 while linear fell 14 minutes and BVoD rose 3. US total TV time is flat at ~3.7h/day but streaming passed broadcast + cable for the first time (47.3%). | D6: Advertisers are not leaving the screen; they are leaving the schedule. CTV inventory is the defended position, not the GRP. | E6: High
A7: 4 | B7: Where time AND money both grow: gaming and live. | C7: Global games USD 188.8bn (+3.4%), with Japan (USD 17.6bn) and Korea (USD 8.3bn) monetising far above their population weight. Live music ~USD 35bn globally; India's organised live events +44% in a single year. | D7: These are the only formats where the two lines move together. They also have no content-amortisation drag relative to video. | E7: Medium-High
A8: 5 | B8: Format choice is national character, not universal law. | C8: Japan: lowest social-media time of any major market (~50 min/day) and TV still the dominant medium (3h37m). Brazil: highest social time in the world (3h49m). Korea: gaming is the largest single format in the country. | D8: There is no 'global consumer'. Benchmarking a market against a global average hides the only thing that matters: its local format mix. | E8: High
A10: Rule | B10: A finding with no number, no source and no implication is an opinion, not a finding.

Sheet 12 Sources
A1: SOURCE REGISTER, every figure in this workbook traces back to one of these
A3: ID | B3: Source | C3: Publisher | D3: Date | E3: Link | F3: What to pull from it
A4: S1 | B4: Ofcom, Media Nations UK 2025 & 2026 | C4: Ofcom | D4: Jul-2025 / Jul-2026 | E4: https://www.ofcom.org.uk/siteassets/resources/documents/research-and-data/multi-sector/media-nations/2026/media-nations-2026-uk-report.pdf | F4: UK: 4h23m daily in-home video (2025); linear 1h51m (-12%); BVoD 28 min; VSP/YouTube 51 min
A5: S2 | B5: Nielsen, The Gauge (US) | C5: Nielsen | D5: 2025 | E5: https://www.nielsen.com/data-center/the-gauge/ | F5: US: 3.7h daily TV time; streaming share 47.3% (Jul-2025); first time streaming > broadcast+cable
A6: S3 | B6: eMarketer, Asia-Pacific Time Spent With Media 2025 | C6: eMarketer | D6: Jul-2025 | E6: https://www.emarketer.com/content/asia-pacific-time-spent-with-media-2025 | F6: Japan TV 3h37m/day; South Korea TV 3h19m/day; digital video below TV in both
A7: S4 | B7: DataReportal / We Are Social / Meltwater, Digital 2025 | C7: DataReportal | D7: Feb-2025 | E7: https://datareportal.com/reports/digital-2025-global-overview-report | F7: Daily internet & social media time by country; social: Brazil 3h49m, US 2h16m, UK 1h37m, Japan ~50m, Korea ~70m
A8: S5 | B8: EY-FICCI, Stories, Scale and Impact (India M&E 2026) | C8: FICCI-EY | D8: Mar-2026 | E8: https://www.ey.com/en_in/insights/media-entertainment/stories-scale-and-impact-unlocking-india-s-m-e-economy | F8: India M&E INR 2.78tn in 2025 (+9%); digital ad INR 947bn (63% of ad spend); live events +44%; CTV ad INR 99bn (+42%)
A9: S6 | B9: Newzoo, Global Games Market Report 2025 | C9: Newzoo | D9: Sep-2025 | E9: https://newzoo.com/resources/blog/global-games-market-to-hit-189-billion-in-2025 | F9: Global games $188.8bn (+3.4%); China $49.8bn; US $49.6bn; Japan $17.6bn; Korea $8.3bn; UK $6.8bn; Brazil $2.8bn
A10: S7 | B10: Niko Partners, India games market | C10: Niko Partners | D10: Aug-2026 | E10: https://nikopartners.com/indias-gaming-market-surpasses-1-billion-for-the-first-time-driven-by-mobile-growth-and-changing-player-behavior/ | F10: India games >$1bn for first time ($1.04bn, +14.8%); 511m players; ARPU $2.04
A11: S8 | B11: Lumikai, State of India Interactive Media 2025 | C11: Lumikai | D11: Mar-2026 | E11: https://respawn.outlookindia.com/gaming/gaming-news/lumikai-india-gaming-market-1-5-billion-rmg-ban-2025 | F11: India video games (ex-RMG) $1.5bn (+17%); gamer base 609m -> 555m (-9%); payer conversion 25%
A12: S9 | B12: IFPI, Global Music Report 2026 | C12: IFPI | D12: Mar-2026 | E12: https://www.musicbusinessworldwide.com/global-recorded-music-revenues-hit-31-7bn-in-2025-up-6-4-yoy-users-of-paid-music-subscriptions-reach-837m/ | F12: Global recorded music $31.7bn (+6.4%); US 38.7% share; ranks: US, Japan, UK, China, Germany, France, Korea, Brazil
A13: S10 | B13: Gower Street Analytics / Comscore / FDA, worldwide box office 2025 | C13: Gower Street | D13: Jan-Apr 2026 | E13: https://filmdistributorsassociation.com/the-industry/databank/worldwide-box-office/top-10-territories/ | F13: Global box office $33.55bn (+12%); US $8.9bn; China $7.4bn; Japan $1.8bn (record); India $1.5bn; UK&I $1.5bn; Korea $0.7bn
A14: S11 | B14: PwC, Global Entertainment & Media Outlook (2025-29, 2026-30) | C14: PwC | D14: Jul-2025 / Aug-2026 | E14: https://www.pwc.com/us/en/industries/tmt/library/global-entertainment-media-outlook.html | F14: Global E&M $2.9tn (2024) -> $3.5tn (2029) -> $4.2tn (2030); US OTT video $113.3bn (2025); US internet ad $419.7bn by 2030
... A23: S20 | B23: The Drum, global media consumption study | C23: The Drum | D23: Mar-2026 | E23: https://www.thedrum.com/news/despite-predicted-downturn-global-media-consumption-grew-yet-again-in-2025 | F23: Global average 8.24 hours of media/day; Japan >13h; US, UK, South Korea >11h
